pydantic2ts/__init__.py
pydantic2ts/cli/__init__.py
pydantic2ts/cli/script.py
pydantic2_to_typescript-0.0.1.dist-info/LICENSE.md
pydantic2_to_typescript-0.0.1.dist-info/METADATA
pydantic2_to_typescript-0.0.1.dist-info/WHEEL
pydantic2_to_typescript-0.0.1.dist-info/entry_points.txt
pydantic2_to_typescript-0.0.1.dist-info/top_level.txt
pydantic2_to_typescript-0.0.1.dist-info/RECORD
