Metadata-Version: 2.1
Name: pydantic2-to-typescript
Version: 0.0.1
Summary: Convert pydantic v2 models to typescript interfaces
Home-page: https://github.com/mukul-mehta/pydantic2-to-typescript
Author: Mukul Mehta
Author-email: work@mukul-mehta.in
License: MIT
Keywords: pydantic typescript annotations validation interface
Classifier: Development Status :: 5 - Production/Stable
Classifier: License :: OSI Approved :: MIT License
Classifier: Programming Language :: Python
Classifier: Programming Language :: Python :: 3
Classifier: Programming Language :: Python :: 3 :: Only
Classifier: Programming Language :: Python :: 3.6
Classifier: Programming Language :: Python :: 3.7
Classifier: Programming Language :: Python :: 3.8
Classifier: Programming Language :: Python :: 3.9
Classifier: Programming Language :: Python :: 3.10
License-File: LICENSE.md
Requires-Dist: pydantic
Provides-Extra: dev
Requires-Dist: pytest ; extra == 'dev'
Requires-Dist: pytest-cov ; extra == 'dev'
Requires-Dist: coverage ; extra == 'dev'
